<?xml version="1.0" encoding="utf-8" ?>
<dwsync>
<file name="bck_main.png" server="C:/wamp/www/FORME" local="129254692540000000" remote="129254692540000000" />
<file name="header.png" server="C:/wamp/www/FORME" local="129254692540000000" remote="129254692540000000" />
<file name="button_glas1.png" server="C:/wamp/www/FORME" local="129254692540000000" remote="129254692540000000" />
<file name="quote.png" server="C:/wamp/www/FORME" local="129254692540000000" remote="129254692540000000" />
<file name="rule.gif" server="C:/wamp/www/FORME" local="129254692540000000" remote="129254692540000000" />
<file name="rule2.gif" server="C:/wamp/www/FORME" local="129254692540000000" remote="129254692540000000" />
<file name="bck_white_10.png" server="C:/wamp/www/FORME" local="129254692540000000" remote="129254692540000000" />
<file name="login.jpg" server="C:/wamp/www/FORME" local="129256272680000000" remote="129256272680000000" />
<file name="login_header.png" server="C:/wamp/www/FORME" local="129254692540000000" remote="129254692540000000" />
<file name="bck_white_50.png" server="C:/wamp/www/FORME" local="129254692540000000" remote="129254692540000000" />
<file name="bck_black_70.png" server="C:/wamp/www/FORME" local="129254692540000000" remote="129254692540000000" />
<file name="breadcrumb.png" server="C:/wamp/www/FORME" local="129254692540000000" remote="129254692540000000" />
<file name="ball_yellow_13.png" server="C:/wamp/www/FORME" local="129254692540000000" remote="129254692540000000" />
<file name="button_glas1_ovr.png" server="C:/wamp/www/FORME" local="129254692540000000" remote="129254692540000000" />
<file name="bck_white_95.png" server="C:/wamp/www/FORME" local="129254692540000000" remote="129254692540000000" />
<file name="arrow_sm_grey.gif" server="C:/wamp/www/FORME" local="129254692540000000" remote="129254692540000000" />
<file name="arrow_sm_black.gif" server="C:/wamp/www/FORME" local="129254692540000000" remote="129254692540000000" />
<file name="line.gif" server="C:/wamp/www/FORME" local="129254692540000000" remote="129254692540000000" />
<file name="bck_white_90.png" server="C:/wamp/www/FORME" local="129254692540000000" remote="129254692540000000" />
<file name="ball_blue_16.png" server="C:/wamp/www/FORME" local="129254692540000000" remote="129254692540000000" />
<file name="ball_green_13.png" server="C:/wamp/www/FORME" local="129254692540000000" remote="129254692540000000" />
<file name="ball_purple_13.png" server="C:/wamp/www/FORME" local="129254692540000000" remote="129254692540000000" />
<file name="ball_black_13.png" server="C:/wamp/www/FORME" local="129254692540000000" remote="129254692540000000" />
<file name="ball_red_13.png" server="C:/wamp/www/FORME" local="129254692540000000" remote="129254692540000000" />
<file name="ball_grey_13.png" server="C:/wamp/www/FORME" local="129254692540000000" remote="129254692540000000" />
<file name="tree_line.gif" server="C:/wamp/www/FORME" local="129254692540000000" remote="129254692540000000" />
<file name="tree_simple.png" server="C:/wamp/www/FORME" local="129254692540000000" remote="129254692540000000" />
<file name="tree_simple_last.png" server="C:/wamp/www/FORME" local="129254692540000000" remote="129254692540000000" />
<file name="tree_point.png" server="C:/wamp/www/FORME" local="129254692540000000" remote="129254692540000000" />
<file name="tree_point_last.png" server="C:/wamp/www/FORME" local="129254692540000000" remote="129254692540000000" />
<file name="bck_header.png" server="C:/wamp/www/FORME" local="129254692540000000" remote="129254692540000000" />
<file name="button_glas2.png" server="C:/wamp/www/FORME" local="129254692540000000" remote="129254692540000000" />
<file name="but_slide.png" server="C:/wamp/www/FORME" local="129254692540000000" remote="129254692540000000" />
<file name="bck_iconbar.png" server="C:/wamp/www/FORME" local="129254692540000000" remote="129254692540000000" />
<file name="bck_iconbar_bottom.png" server="C:/wamp/www/FORME" local="129254692540000000" remote="129254692540000000" />
<file name="arrowleft_iconbar_off.png" server="C:/wamp/www/FORME" local="129254692540000000" remote="129254692540000000" />
<file name="arrowleft_iconbar_act.png" server="C:/wamp/www/FORME" local="129254692540000000" remote="129254692540000000" />
<file name="arrowleft_iconbar_ovr.png" server="C:/wamp/www/FORME" local="129254692540000000" remote="129254692540000000" />
<file name="arrowright_iconbar_off.png" server="C:/wamp/www/FORME" local="129254692540000000" remote="129254692540000000" />
<file name="arrowright_iconbar_act.png" server="C:/wamp/www/FORME" local="129254692540000000" remote="129254692540000000" />
<file name="arrowright_iconbar_ovr.png" server="C:/wamp/www/FORME" local="129254692540000000" remote="129254692540000000" />
<file name="bck_iconbar_ovr.png" server="C:/wamp/www/FORME" local="129254692540000000" remote="129254692540000000" />
<file name="bck_sidebar.png" server="C:/wamp/www/FORME" local="129254692540000000" remote="129254692540000000" />
<file name="ui-bg_glass_100_f6f6f6_1x400.png" server="C:/wamp/www/FORME" local="129254692540000000" remote="129254692540000000" />
<file name="arrow_sm_blue.gif" server="C:/wamp/www/FORME" local="129254692540000000" remote="129254692540000000" />
<file name="bck_black_10.png" server="C:/wamp/www/FORME" local="129254692540000000" remote="129254692540000000" />
<file name="bck_black_5.png" server="C:/wamp/www/FORME" local="129254692540000000" remote="129254692540000000" />
<file name="bck_white_75.png" server="C:/wamp/www/FORME" local="129254692540000000" remote="129254692540000000" />
<file name="arrow_leftend_off.png" server="C:/wamp/www/FORME" local="129254692540000000" remote="129254692540000000" />
<file name="arrow_leftend_ovr.png" server="C:/wamp/www/FORME" local="129254692540000000" remote="129254692540000000" />
<file name="arrow_left_off.png" server="C:/wamp/www/FORME" local="129254692540000000" remote="129254692540000000" />
<file name="arrow_left_ovr.png" server="C:/wamp/www/FORME" local="129254692540000000" remote="129254692540000000" />
<file name="arrow_rightend_off.png" server="C:/wamp/www/FORME" local="129254692540000000" remote="129254692540000000" />
<file name="arrow_rightend_ovr.png" server="C:/wamp/www/FORME" local="129254692540000000" remote="129254692540000000" />
<file name="arrow_right_off.png" server="C:/wamp/www/FORME" local="129254692540000000" remote="129254692540000000" />
<file name="arrow_right_ovr.png" server="C:/wamp/www/FORME" local="129254692540000000" remote="129254692540000000" />
<file name="page_active.gif" server="C:/wamp/www/FORME" local="129254692540000000" remote="129254692540000000" />
<file name="ico_close_off.png" server="C:/wamp/www/FORME" local="129254692540000000" remote="129254692540000000" />
<file name="ico_close_ovr.png" server="C:/wamp/www/FORME" local="129254692540000000" remote="129254692540000000" />
<file name="ico_error.png" server="C:/wamp/www/FORME" local="129254692540000000" remote="129254692540000000" />
<file name="ico_success.png" server="C:/wamp/www/FORME" local="129254692540000000" remote="129254692540000000" />
<file name="ico_info.png" server="C:/wamp/www/FORME" local="129254692540000000" remote="129254692540000000" />
<file name="ico_attention.png" server="C:/wamp/www/FORME" local="129254692540000000" remote="129254692540000000" />
<file name="arrow_sm_black_top.gif" server="C:/wamp/www/FORME" local="129254692540000000" remote="129254692540000000" />
<file name="arrow_sm_black_down.gif" server="C:/wamp/www/FORME" local="129254692540000000" remote="129254692540000000" />
<file name="ico_graph_16_off.png" server="C:/wamp/www/FORME" local="129254692540000000" remote="129254692540000000" />
<file name="ico_graph_16_ovr.png" server="C:/wamp/www/FORME" local="129254692540000000" remote="129254692540000000" />
<file name="ico_shopping_16_off.png" server="C:/wamp/www/FORME" local="129254692540000000" remote="129254692540000000" />
<file name="ico_shopping_16_ovr.png" server="C:/wamp/www/FORME" local="129254692540000000" remote="129254692540000000" />
<file name="ico_history_16_off.png" server="C:/wamp/www/FORME" local="129254692540000000" remote="129254692540000000" />
<file name="ico_history_16_ovr.png" server="C:/wamp/www/FORME" local="129254692540000000" remote="129254692540000000" />
<file name="envelope_off.png" server="C:/wamp/www/FORME" local="129254692540000000" remote="129254692540000000" />
<file name="envelope_ovr.png" server="C:/wamp/www/FORME" local="129254692540000000" remote="129254692540000000" />
<file name="user_male.png" server="C:/wamp/www/FORME" local="129254692540000000" remote="129254692540000000" />
<file name="user_female.png" server="C:/wamp/www/FORME" local="129254692540000000" remote="129254692540000000" />
<file name="bck_icon48_dark.png" server="C:/wamp/www/FORME" local="129254692540000000" remote="129254692540000000" />
<file name="ball_red_16.png" server="C:/wamp/www/FORME" local="129254692540000000" remote="129254692540000000" />
<file name="ball_yellow_16.png" server="C:/wamp/www/FORME" local="129254692540000000" remote="129254692540000000" />
<file name="ico_edit_16.png" server="C:/wamp/www/FORME" local="129254692540000000" remote="129254692540000000" />
<file name="ico_edit_12.png" server="C:/wamp/www/FORME" local="129254692540000000" remote="129254692540000000" />
<file name="ico_delete_12.png" server="C:/wamp/www/FORME" local="129254692540000000" remote="129254692540000000" />
<file name="jquery.wysiwyg.gif" server="C:/wamp/www/FORME" local="129254692540000000" remote="129254692540000000" />
<file name="chart-x.gif" server="C:/wamp/www/FORME" local="129254692540000000" remote="129254692540000000" />
<file name="avatar.jpg" server="C:/wamp/www/FORME" local="129254692540000000" remote="129254692540000000" />
<file name="logo_earth.png" server="C:/wamp/www/FORME" local="129254692540000000" remote="129254692540000000" />
<file name="ico_folder_64.png" server="C:/wamp/www/FORME" local="129254692540000000" remote="129254692540000000" />
<file name="ico_page_64.png" server="C:/wamp/www/FORME" local="129254692540000000" remote="129254692540000000" />
<file name="ico_picture_64.png" server="C:/wamp/www/FORME" local="129254692540000000" remote="129254692540000000" />
<file name="ico_clock_64.png" server="C:/wamp/www/FORME" local="129254692540000000" remote="129254692540000000" />
<file name="ico_users_64.png" server="C:/wamp/www/FORME" local="129254692540000000" remote="129254692540000000" />
<file name="ico_settings_64.png" server="C:/wamp/www/FORME" local="129254692540000000" remote="129254692540000000" />
<file name="ico_chat_64.png" server="C:/wamp/www/FORME" local="129254692540000000" remote="129254692540000000" />
<file name="ico_delete_16.png" server="C:/wamp/www/FORME" local="129254692540000000" remote="129254692540000000" />
<file name="ico_settings_16.png" server="C:/wamp/www/FORME" local="129254692540000000" remote="129254692540000000" />
<file name="ico_active_16.png" server="C:/wamp/www/FORME" local="129254692540000000" remote="129254692540000000" />
<file name="ico_inactive_16.png" server="C:/wamp/www/FORME" local="129254692540000000" remote="129254692540000000" />
<file name="logo_earth_bw50.png" server="C:/wamp/www/FORME" local="129256272680000000" remote="129256272680000000" />
<file name="acceuil.jpg" server="C:/wamp/www/FORME" local="129456555230636164" remote="129456555230000000" />
<file name="bck_main.png" server="C:/wamp/www/version0/final/" local="129254656540000000" remote="129254656540000000" />
<file name="header.png" server="C:/wamp/www/version0/final/" local="129254656540000000" remote="129254656540000000" />
<file name="button_glas1.png" server="C:/wamp/www/version0/final/" local="129254656540000000" remote="129254656540000000" />
<file name="quote.png" server="C:/wamp/www/version0/final/" local="129254656540000000" remote="129254656540000000" />
<file name="rule.gif" server="C:/wamp/www/version0/final/" local="129490150660000000" remote="129490150660000000" />
<file name="rule2.gif" server="C:/wamp/www/version0/final/" local="129254656540000000" remote="129254656540000000" />
<file name="bck_white_10.png" server="C:/wamp/www/version0/final/" local="129254656540000000" remote="129254656540000000" />
<file name="login.jpg" server="C:/wamp/www/version0/final/" local="129256236680000000" remote="129256236680000000" />
<file name="login_header.png" server="C:/wamp/www/version0/final/" local="129254656540000000" remote="129254656540000000" />
<file name="bck_white_50.png" server="C:/wamp/www/version0/final/" local="129254656540000000" remote="129254656540000000" />
<file name="bck_black_70.png" server="C:/wamp/www/version0/final/" local="129254656540000000" remote="129254656540000000" />
<file name="breadcrumb.png" server="C:/wamp/www/version0/final/" local="129254656540000000" remote="129254656540000000" />
<file name="ball_yellow_13.png" server="C:/wamp/www/version0/final/" local="129254656540000000" remote="129254656540000000" />
<file name="button_glas1_ovr.png" server="C:/wamp/www/version0/final/" local="129254656540000000" remote="129254656540000000" />
<file name="bck_white_95.png" server="C:/wamp/www/version0/final/" local="129254656540000000" remote="129254656540000000" />
<file name="arrow_sm_grey.gif" server="C:/wamp/www/version0/final/" local="129254656540000000" remote="129254656540000000" />
<file name="arrow_sm_black.gif" server="C:/wamp/www/version0/final/" local="129254656540000000" remote="129254656540000000" />
<file name="line.gif" server="C:/wamp/www/version0/final/" local="129254656540000000" remote="129254656540000000" />
<file name="bck_white_90.png" server="C:/wamp/www/version0/final/" local="129254656540000000" remote="129254656540000000" />
<file name="ball_blue_16.png" server="C:/wamp/www/version0/final/" local="129254656540000000" remote="129254656540000000" />
<file name="ball_green_13.png" server="C:/wamp/www/version0/final/" local="129254656540000000" remote="129254656540000000" />
<file name="ball_purple_13.png" server="C:/wamp/www/version0/final/" local="129254656540000000" remote="129254656540000000" />
<file name="ball_black_13.png" server="C:/wamp/www/version0/final/" local="129254656540000000" remote="129254656540000000" />
<file name="ball_red_13.png" server="C:/wamp/www/version0/final/" local="129254656540000000" remote="129254656540000000" />
<file name="ball_grey_13.png" server="C:/wamp/www/version0/final/" local="129254656540000000" remote="129254656540000000" />
<file name="tree_line.gif" server="C:/wamp/www/version0/final/" local="129254656540000000" remote="129254656540000000" />
<file name="tree_simple.png" server="C:/wamp/www/version0/final/" local="129254656540000000" remote="129254656540000000" />
<file name="tree_simple_last.png" server="C:/wamp/www/version0/final/" local="129254656540000000" remote="129254656540000000" />
<file name="tree_point.png" server="C:/wamp/www/version0/final/" local="129254656540000000" remote="129254656540000000" />
<file name="tree_point_last.png" server="C:/wamp/www/version0/final/" local="129254656540000000" remote="129254656540000000" />
<file name="bck_header.png" server="C:/wamp/www/version0/final/" local="129254656540000000" remote="129254656540000000" />
<file name="button_glas2.png" server="C:/wamp/www/version0/final/" local="129254656540000000" remote="129254656540000000" />
<file name="but_slide.png" server="C:/wamp/www/version0/final/" local="129254656540000000" remote="129254656540000000" />
<file name="bck_iconbar.png" server="C:/wamp/www/version0/final/" local="129254656540000000" remote="129254656540000000" />
<file name="bck_iconbar_bottom.png" server="C:/wamp/www/version0/final/" local="129254656540000000" remote="129254656540000000" />
<file name="arrowleft_iconbar_off.png" server="C:/wamp/www/version0/final/" local="129254656540000000" remote="129254656540000000" />
<file name="arrowleft_iconbar_act.png" server="C:/wamp/www/version0/final/" local="129254656540000000" remote="129254656540000000" />
<file name="arrowleft_iconbar_ovr.png" server="C:/wamp/www/version0/final/" local="129254656540000000" remote="129254656540000000" />
<file name="arrowright_iconbar_off.png" server="C:/wamp/www/version0/final/" local="129254656540000000" remote="129254656540000000" />
<file name="arrowright_iconbar_act.png" server="C:/wamp/www/version0/final/" local="129254656540000000" remote="129254656540000000" />
<file name="arrowright_iconbar_ovr.png" server="C:/wamp/www/version0/final/" local="129254656540000000" remote="129254656540000000" />
<file name="bck_iconbar_ovr.png" server="C:/wamp/www/version0/final/" local="129254656540000000" remote="129254656540000000" />
<file name="bck_sidebar.png" server="C:/wamp/www/version0/final/" local="129254656540000000" remote="129254656540000000" />
<file name="ui-bg_glass_100_f6f6f6_1x400.png" server="C:/wamp/www/version0/final/" local="129254656540000000" remote="129254656540000000" />
<file name="arrow_sm_blue.gif" server="C:/wamp/www/version0/final/" local="129254656540000000" remote="129254656540000000" />
<file name="bck_black_10.png" server="C:/wamp/www/version0/final/" local="129254656540000000" remote="129254656540000000" />
<file name="bck_black_5.png" server="C:/wamp/www/version0/final/" local="129254656540000000" remote="129254656540000000" />
<file name="bck_white_75.png" server="C:/wamp/www/version0/final/" local="129254656540000000" remote="129254656540000000" />
<file name="arrow_leftend_off.png" server="C:/wamp/www/version0/final/" local="129254656540000000" remote="129254656540000000" />
<file name="arrow_leftend_ovr.png" server="C:/wamp/www/version0/final/" local="129254656540000000" remote="129254656540000000" />
<file name="arrow_left_off.png" server="C:/wamp/www/version0/final/" local="129254656540000000" remote="129254656540000000" />
<file name="arrow_left_ovr.png" server="C:/wamp/www/version0/final/" local="129254656540000000" remote="129254656540000000" />
<file name="arrow_rightend_off.png" server="C:/wamp/www/version0/final/" local="129254656540000000" remote="129254656540000000" />
<file name="arrow_rightend_ovr.png" server="C:/wamp/www/version0/final/" local="129254656540000000" remote="129254656540000000" />
<file name="arrow_right_off.png" server="C:/wamp/www/version0/final/" local="129254656540000000" remote="129254656540000000" />
<file name="arrow_right_ovr.png" server="C:/wamp/www/version0/final/" local="129254656540000000" remote="129254656540000000" />
<file name="page_active.gif" server="C:/wamp/www/version0/final/" local="129254656540000000" remote="129254656540000000" />
<file name="ico_close_off.png" server="C:/wamp/www/version0/final/" local="129254656540000000" remote="129254656540000000" />
<file name="ico_close_ovr.png" server="C:/wamp/www/version0/final/" local="129254656540000000" remote="129254656540000000" />
<file name="ico_error.png" server="C:/wamp/www/version0/final/" local="129254656540000000" remote="129254656540000000" />
<file name="ico_success.png" server="C:/wamp/www/version0/final/" local="129254656540000000" remote="129254656540000000" />
<file name="ico_info.png" server="C:/wamp/www/version0/final/" local="129254656540000000" remote="129254656540000000" />
<file name="ico_attention.png" server="C:/wamp/www/version0/final/" local="129254656540000000" remote="129254656540000000" />
<file name="arrow_sm_black_top.gif" server="C:/wamp/www/version0/final/" local="129254656540000000" remote="129254656540000000" />
<file name="arrow_sm_black_down.gif" server="C:/wamp/www/version0/final/" local="129254656540000000" remote="129254656540000000" />
<file name="ico_graph_16_off.png" server="C:/wamp/www/version0/final/" local="129254656540000000" remote="129254656540000000" />
<file name="ico_graph_16_ovr.png" server="C:/wamp/www/version0/final/" local="129254656540000000" remote="129254656540000000" />
<file name="ico_shopping_16_off.png" server="C:/wamp/www/version0/final/" local="129254656540000000" remote="129254656540000000" />
<file name="ico_shopping_16_ovr.png" server="C:/wamp/www/version0/final/" local="129254656540000000" remote="129254656540000000" />
<file name="ico_history_16_off.png" server="C:/wamp/www/version0/final/" local="129254656540000000" remote="129254656540000000" />
<file name="ico_history_16_ovr.png" server="C:/wamp/www/version0/final/" local="129254656540000000" remote="129254656540000000" />
<file name="envelope_off.png" server="C:/wamp/www/version0/final/" local="129254656540000000" remote="129254656540000000" />
<file name="envelope_ovr.png" server="C:/wamp/www/version0/final/" local="129254656540000000" remote="129254656540000000" />
<file name="user_male.png" server="C:/wamp/www/version0/final/" local="129254656540000000" remote="129254656540000000" />
<file name="user_female.png" server="C:/wamp/www/version0/final/" local="129254656540000000" remote="129254656540000000" />
<file name="bck_icon48_dark.png" server="C:/wamp/www/version0/final/" local="129254656540000000" remote="129254656540000000" />
<file name="ball_red_16.png" server="C:/wamp/www/version0/final/" local="129254656540000000" remote="129254656540000000" />
<file name="ball_yellow_16.png" server="C:/wamp/www/version0/final/" local="129254656540000000" remote="129254656540000000" />
<file name="ico_edit_16.png" server="C:/wamp/www/version0/final/" local="129254656540000000" remote="129254656540000000" />
<file name="ico_edit_12.png" server="C:/wamp/www/version0/final/" local="129254656540000000" remote="129254656540000000" />
<file name="ico_delete_12.png" server="C:/wamp/www/version0/final/" local="129254656540000000" remote="129254656540000000" />
</dwsync>